textblob_de/__init__.py
textblob_de/base.py
textblob_de/blob.py
textblob_de/classifiers.py
textblob_de/compat.py
textblob_de/lemmatizers.py
textblob_de/np_extractors.py
textblob_de/packages.py
textblob_de/parsers.py
textblob_de/sentiments.py
textblob_de/taggers.py
textblob_de/tokenizers.py
textblob_de/data/de-sentiment.xml
textblob_de/ext/_pattern/__init__.py
textblob_de/ext/_pattern/compat.py
textblob_de/ext/_pattern/text/__init__.py
textblob_de/ext/_pattern/text/search.py
textblob_de/ext/_pattern/text/tree.py
textblob_de/ext/_pattern/text/de/__init__.py
textblob_de/ext/_pattern/text/de/__main__.py
textblob_de/ext/_pattern/text/de/de-context.txt
textblob_de/ext/_pattern/text/de/de-frequency.txt
textblob_de/ext/_pattern/text/de/de-lexicon.txt
textblob_de/ext/_pattern/text/de/de-morphology.txt
textblob_de/ext/_pattern/text/de/de-verbs.txt
textblob_de/ext/_pattern/text/de/inflect.py
textblob_de-0.4.3.dist-info/AUTHORS.rst
textblob_de-0.4.3.dist-info/LICENSE
textblob_de-0.4.3.dist-info/METADATA
textblob_de-0.4.3.dist-info/NOTICE
textblob_de-0.4.3.dist-info/WHEEL
textblob_de-0.4.3.dist-info/top_level.txt
textblob_de-0.4.3.dist-info/RECORD
